haystack_opea/__init__.py
haystack_opea/embedders/__init__.py
haystack_opea/embedders/tei/__init__.py
haystack_opea/embedders/tei/document_embedder.py
haystack_opea/embedders/tei/text_embedder.py
haystack_opea/embedders/tei/truncate.py
haystack_opea/generators/__init__.py
haystack_opea/generators/generator.py
haystack_opea/utils/__init__.py
haystack_opea/utils/opea_backend.py
haystack_opea/utils/utils.py
haystack_opea-0.1.2.dist-info/LICENSE
haystack_opea-0.1.2.dist-info/METADATA
haystack_opea-0.1.2.dist-info/WHEEL
haystack_opea-0.1.2.dist-info/RECORD
