Metadata-Version: 2.3
Name: haystack-opea
Version: 0.1.2
Summary: An integration package connecting OPEA and Haystack
License: Apache-2.0
Author: Daniel Fleischer
Author-email: daniel.fleischer@intel.com
Requires-Python: >=3.9
Classifier: License :: OSI Approved :: Apache Software License
Classifier: Programming Language :: Python :: 3
Classifier: Programming Language :: Python :: 3.9
Classifier: Programming Language :: Python :: 3.10
Classifier: Programming Language :: Python :: 3.11
Classifier: Programming Language :: Python :: 3.12
Classifier: Programming Language :: Python :: 3.13
Requires-Dist: h11 (>=0.16.0,<0.17.0)
Requires-Dist: haystack-ai (>=2,<3)
Project-URL: Homepage, https://github.com/deepset-ai/haystack/
Project-URL: Repository, https://github.com/opea-project/Haystack-OPEA
